Workbook
Name Slicer_Coffee_Type: #N/A
Name Slicer_Country: #N/A
Name Slicer_Roast_Type: #N/A
Name Slicer_Sales_Category: #N/A
Name Slicer_Weekday: #N/A
Name Slicer_Year: #N/A

Sheet Dashboard

Sheet sales by coffee type
A3: Sum of Sales | B3: Column Labels
A4: Row Labels | B4: High sales | C4: low sales | D4: medium sales | E4: Grand Total
A5: Ara | B5: 4605.06 | C5: 4006.285 | D5: 3157.15 | E5: 11768.495
A6: Exc | B6: 4645.195 | C6: 3635.175 | D6: 4026.07 | E6: 12306.44
A7: Lib | B7: 4524.56 | C7: 3984.985 | D7: 3544.53 | E7: 12054.075
A8: Rob | B8: 2596.01 | C8: 3916.135 | D8: 2493.1 | E8: 9005.245
A9: Grand Total | B9: 16370.825 | C9: 15542.58 | D9: 13220.85 | E9: 45134.255

Sheet Trend Analysis
A3: Sum of Sales | B3: Column Labels
A4: Row Labels | B4: Ara | C4: Exc | D4: Lib | E4: Rob | F4: Grand Total
A5: 2019 | B5: 2926.63 | C5: 3481.46 | D5: 3378.005 | E5: 2401.07 | F5: 12187.165
A6: 2020 | B6: 3356.415 | C6: 3663.41 | D6: 2604.455 | E6: 2493.265 | F6: 12117.545
A7: 2021 | B7: 4045.63 | C7: 3469.64 | D7: 3836.695 | E7: 2414.145 | F7: 13766.11
A8: 2022 | B8: 1439.82 | C8: 1691.93 | D8: 2234.92 | E8: 1696.765 | F8: 7063.435
A9: Grand Total | B9: 11768.495 | C9: 12306.44 | D9: 12054.075 | E9: 9005.245 | F9: 45134.255

Sheet Average Weekly Sales
A3: Row Labels | B3: Average of Sales
A4: Sunday | B4: 51.116964
A5: Monday | B5: 43.564161
A6: Tuesday | B6: 38.503241
A7: Wednesday | B7: 44.909155
A8: Thursday | B8: 45.741713
A9: Friday | B9: 45.948019
A10: Saturday | B10: 46.288955
A11: Grand Total | B11: 45.134255

Sheet Sales Contribution
A3: Row Labels | B3: Sum of Sales
A4: High sales | B4: 16370.825
A5: low sales | B5: 15542.58
A6: medium sales | B6: 13220.85
A7: Grand Total | B7: 45134.255

Sheet Sales By Roast Type
A3: Row Labels | B3: Sum of Sales
A4: D | B4: 13179.315
A5: L | B5: 17354.465
A6: M | B6: 14600.475
A7: Grand Total | B7: 45134.255

Sheet Top 5 Customer Sales
A3: Row Labels | B3: Sum of Sales
A4: Allis Wilmore | B4: 317.07
A5: Brenn Dundredge | B5: 307.045
A6: Terri Farra | B6: 289.11
A7: Nealson Cuttler | B7: 281.675
A8: Don Flintiff | B8: 278.01
A9: Grand Total | B9: 1472.91

Sheet Top 5 Cities By Sales
A3: Row Labels | B3: Sum of Sales
A4: Washington | B4: 1066.92
A5: Houston | B5: 819.77
A6: Toledo | B6: 774.185
A7: New York City | B7: 772.735
A8: Sacramento | B8: 627.75
A9: Grand Total | B9: 4061.36

Sheet Combination Chart
A3: Row Labels | B3: Sum of Sales | C3: Sum of Quantity
A4: Ara | B4: 11768.495 | C4: 947
A5: Exc | B5: 12306.44 | C5: 872
A6: Lib | B6: 12054.075 | C6: 854
A7: Rob | B7: 9005.245 | C7: 878
A8: Grand Total | B8: 45134.255 | C8: 3551

Sheet orders
A1: Order ID | B1: Order Date | C1: Weekday | D1: Month | E1: Year | F1: Customer ID | G1: Product ID | H1: Quantity | I1: Customer Name | J1: Email | K1: city | L1: Country | M1: Coffee Type | N1: Roast Type | O1: Size | P1: Unit Price | Q1: Sales | R1: Sales Category
A2: QEV-37451-860 | B2: 43713 | C2: =TEXT(B2,"DDDD") -> Thursday | D2: =TEXT(B2,"MMMM") -> September | E2: =TEXT(B2,"YYYY") -> 2019 | F2: 17670-51384-MA | G2: R-M-1 | H2: 2 | I2: =_xlfn.XLOOKUP(F2,customers!A:A,customers!B:B) -> Aloisia Allner | J2: =_xlfn.XLOOKUP(F2,customers!A:A,customers!C:C) -> aallner0@lulu.com | K2: =_xlfn.XLOOKUP(F2,customers!A:A,customers!F:F) -> Paterson | L2: =_xlfn.XLOOKUP(F2,customers!A:A,customers!G:G) -> United States | M2: =_xlfn.XLOOKUP(G2,products!A:A,products!B:B) -> Rob | N2: =_xlfn.XLOOKUP(G2,products!A:A,products!C:C) -> M | O2: =_xlfn.XLOOKUP(G2,products!A:A,products!D:D) -> 1 | P2: =_xlfn.XLOOKUP(G2,products!A:A,products!E:E) -> 9.95 | Q2: =P2*H2 -> 19.9 | R2: {=_xlfn.IFS(Q2<=50,"low sales",Q2<=100,"medium sales",Q2>100,"High sales")} -> low sales
A3: QEV-37451-860 | B3: 43713 | C3: =TEXT(B3,"DDDD") -> Thursday | D3: =TEXT(B3,"MMMM") -> September | E3: =TEXT(B3,"YYYY") -> 2019 | F3: 17670-51384-MA | G3: E-M-0.5 | H3: 5 | I3: =_xlfn.XLOOKUP(F3,customers!A:A,customers!B:B) -> Aloisia Allner | J3: =_xlfn.XLOOKUP(F3,customers!A:A,customers!C:C) -> aallner0@lulu.com | K3: =_xlfn.XLOOKUP(F3,customers!A:A,customers!F:F) -> Paterson | L3: =_xlfn.XLOOKUP(F3,customers!A:A,customers!G:G) -> United States | M3: =_xlfn.XLOOKUP(G3,products!A:A,products!B:B) -> Exc | N3: =_xlfn.XLOOKUP(G3,products!A:A,products!C:C) -> M | O3: =_xlfn.XLOOKUP(G3,products!A:A,products!D:D) -> 0.5 | P3: =_xlfn.XLOOKUP(G3,products!A:A,products!E:E) -> 8.25 | Q3: =P3*H3 -> 41.25 | R3: {=_xlfn.IFS(Q3<=50,"low sales",Q3<=100,"medium sales",Q3>100,"High sales")} -> low sales
A4: FAA-43335-268 | B4: 44364 | C4: =TEXT(B4,"DDDD") -> Thursday | D4: =TEXT(B4,"MMMM") -> June | E4: =TEXT(B4,"YYYY") -> 2021 | F4: 21125-22134-PX | G4: A-L-1 | H4: 1 | I4: =_xlfn.XLOOKUP(F4,customers!A:A,customers!B:B) -> Jami Redholes | J4: =_xlfn.XLOOKUP(F4,customers!A:A,customers!C:C) -> jredholes2@tmall.com | K4: =_xlfn.XLOOKUP(F4,customers!A:A,customers!F:F) -> San Antonio | L4: =_xlfn.XLOOKUP(F4,customers!A:A,customers!G:G) -> United States | M4: =_xlfn.XLOOKUP(G4,products!A:A,products!B:B) -> Ara | N4: =_xlfn.XLOOKUP(G4,products!A:A,products!C:C) -> L | O4: =_xlfn.XLOOKUP(G4,products!A:A,products!D:D) -> 1 | P4: =_xlfn.XLOOKUP(G4,products!A:A,products!E:E) -> 12.95 | Q4: =P4*H4 -> 12.95 | R4: {=_xlfn.IFS(Q4<=50,"low sales",Q4<=100,"medium sales",Q4>100,"High sales")} -> low sales
A5: KAC-83089-793 | B5: 44392 | C5: =TEXT(B5,"DDDD") -> Thursday | D5: =TEXT(B5,"MMMM") -> July | E5: =TEXT(B5,"YYYY") -> 2021 | F5: 23806-46781-OU | G5: E-M-1 | H5: 2 | I5: =_xlfn.XLOOKUP(F5,customers!A:A,customers!B:B) -> Christoffer O' Shea | J5: =_xlfn.XLOOKUP(F5,customers!A:A,customers!C:C) -> 0 | K5: =_xlfn.XLOOKUP(F5,customers!A:A,customers!F:F) -> Cill Airne | L5: =_xlfn.XLOOKUP(F5,customers!A:A,customers!G:G) -> Ireland | M5: =_xlfn.XLOOKUP(G5,products!A:A,products!B:B) -> Exc | N5: =_xlfn.XLOOKUP(G5,products!A:A,products!C:C) -> M | O5: =_xlfn.XLOOKUP(G5,products!A:A,products!D:D) -> 1 | P5: =_xlfn.XLOOKUP(G5,products!A:A,products!E:E) -> 13.75 | Q5: =P5*H5 -> 27.5 | R5: {=_xlfn.IFS(Q5<=50,"low sales",Q5<=100,"medium sales",Q5>100,"High sales")} -> low sales
A6: KAC-83089-793 | B6: 44392 | C6: =TEXT(B6,"DDDD") -> Thursday | D6: =TEXT(B6,"MMMM") -> July | E6: =TEXT(B6,"YYYY") -> 2021 | F6: 23806-46781-OU | G6: R-L-2.5 | H6: 2 | I6: =_xlfn.XLOOKUP(F6,customers!A:A,customers!B:B) -> Christoffer O' Shea | J6: =_xlfn.XLOOKUP(F6,customers!A:A,customers!C:C) -> 0 | K6: =_xlfn.XLOOKUP(F6,customers!A:A,customers!F:F) -> Cill Airne | L6: =_xlfn.XLOOKUP(F6,customers!A:A,customers!G:G) -> Ireland | M6: =_xlfn.XLOOKUP(G6,products!A:A,products!B:B) -> Rob | N6: =_xlfn.XLOOKUP(G6,products!A:A,products!C:C) -> L | O6: =_xlfn.XLOOKUP(G6,products!A:A,products!D:D) -> 2.5 | P6: =_xlfn.XLOOKUP(G6,products!A:A,products!E:E) -> 27.485 | Q6: =P6*H6 -> 54.97 | R6: {=_xlfn.IFS(Q6<=50,"low sales",Q6<=100,"medium sales",Q6>100,"High sales")} -> medium sales
A7: CVP-18956-553 | B7: 44412 | C7: =TEXT(B7,"DDDD") -> Wednesday | D7: =TEXT(B7,"MMMM") -> August | E7: =TEXT(B7,"YYYY") -> 2021 | F7: 86561-91660-RB | G7: L-D-1 | H7: 3 | I7: =_xlfn.XLOOKUP(F7,customers!A:A,customers!B:B) -> Beryle Cottier | J7: =_xlfn.XLOOKUP(F7,customers!A:A,customers!C:C) -> 0 | K7: =_xlfn.XLOOKUP(F7,customers!A:A,customers!F:F) -> Scranton | L7: =_xlfn.XLOOKUP(F7,customers!A:A,customers!G:G) -> United States | M7: =_xlfn.XLOOKUP(G7,products!A:A,products!B:B) -> Lib | N7: =_xlfn.XLOOKUP(G7,products!A:A,products!C:C) -> D | O7: =_xlfn.XLOOKUP(G7,products!A:A,products!D:D) -> 1 | P7: =_xlfn.XLOOKUP(G7,products!A:A,products!E:E) -> 12.95 | Q7: =P7*H7 -> 38.85 | R7: {=_xlfn.IFS(Q7<=50,"low sales",Q7<=100,"medium sales",Q7>100,"High sales")} -> low sales
A8: IPP-31994-879 | B8: 44582 | C8: =TEXT(B8,"DDDD") -> Friday | D8: =TEXT(B8,"MMMM") -> January | E8: =TEXT(B8,"YYYY") -> 2022 | F8: 65223-29612-CB | G8: E-D-0.5 | H8: 3 | I8: =_xlfn.XLOOKUP(F8,customers!A:A,customers!B:B) -> Shaylynn Lobe | J8: =_xlfn.XLOOKUP(F8,customers!A:A,customers!C:C) -> slobe6@nifty.com | K8: =_xlfn.XLOOKUP(F8,customers!A:A,customers!F:F) -> Dayton | L8: =_xlfn.XLOOKUP(F8,customers!A:A,customers!G:G) -> United States | M8: =_xlfn.XLOOKUP(G8,products!A:A,products!B:B) -> Exc | N8: =_xlfn.XLOOKUP(G8,products!A:A,products!C:C) -> D | O8: =_xlfn.XLOOKUP(G8,products!A:A,products!D:D) -> 0.5 | P8: =_xlfn.XLOOKUP(G8,products!A:A,products!E:E) -> 7.29 | Q8: =P8*H8 -> 21.87 | R8: {=_xlfn.IFS(Q8<=50,"low sales",Q8<=100,"medium sales",Q8>100,"High sales")} -> low sales
A9: SNZ-65340-705 | B9: 44701 | C9: =TEXT(B9,"DDDD") -> Friday | D9: =TEXT(B9,"MMMM") -> May | E9: =TEXT(B9,"YYYY") -> 2022 | F9: 21134-81676-FR | G9: L-L-0.2 | H9: 1 | I9: =_xlfn.XLOOKUP(F9,customers!A:A,customers!B:B) -> Melvin Wharfe | J9: =_xlfn.XLOOKUP(F9,customers!A:A,customers!C:C) -> 0 | K9: =_xlfn.XLOOKUP(F9,customers!A:A,customers!F:F) -> Kill | L9: =_xlfn.XLOOKUP(F9,customers!A:A,customers!G:G) -> Ireland | M9: =_xlfn.XLOOKUP(G9,products!A:A,products!B:B) -> Lib | N9: =_xlfn.XLOOKUP(G9,products!A:A,products!C:C) -> L | O9: =_xlfn.XLOOKUP(G9,products!A:A,products!D:D) -> 0.2 | P9: =_xlfn.XLOOKUP(G9,products!A:A,products!E:E) -> 4.755 | Q9: =P9*H9 -> 4.755 | R9: {=_xlfn.IFS(Q9<=50,"low sales",Q9<=100,"medium sales",Q9>100,"High sales")} -> low sales
A10: EZT-46571-659 | B10: 43467 | C10: =TEXT(B10,"DDDD") -> Wednesday | D10: =TEXT(B10,"MMMM") -> January | E10: =TEXT(B10,"YYYY") -> 2019 | F10: 03396-68805-ZC | G10: R-M-0.5 | H10: 3 | I10: =_xlfn.XLOOKUP(F10,customers!A:A,customers!B:B) -> Guthrey Petracci | J10: =_xlfn.XLOOKUP(F10,customers!A:A,customers!C:C) -> gpetracci8@livejournal.com | K10: =_xlfn.XLOOKUP(F10,customers!A:A,customers!F:F) -> Los Angeles | L10: =_xlfn.XLOOKUP(F10,customers!A:A,customers!G:G) -> United States | M10: =_xlfn.XLOOKUP(G10,products!A:A,products!B:B) -> Rob | N10: =_xlfn.XLOOKUP(G10,products!A:A,products!C:C) -> M | O10: =_xlfn.XLOOKUP(G10,products!A:A,products!D:D) -> 0.5 | P10: =_xlfn.XLOOKUP(G10,products!A:A,products!E:E) -> 5.97 | Q10: =P10*H10 -> 17.91 | R10: {=_xlfn.IFS(Q10<=50,"low sales",Q10<=100,"medium sales",Q10>100,"High sales")} -> low sales
A11: NWQ-70061-912 | B11: 43713 | C11: =TEXT(B11,"DDDD") -> Thursday | D11: =TEXT(B11,"MMMM") -> September | E11: =TEXT(B11,"YYYY") -> 2019 | F11: 61021-27840-ZN | G11: R-M-0.5 | H11: 1 | I11: =_xlfn.XLOOKUP(F11,customers!A:A,customers!B:B) -> Rodger Raven | J11: =_xlfn.XLOOKUP(F11,customers!A:A,customers!C:C) -> rraven9@ed.gov | K11: =_xlfn.XLOOKUP(F11,customers!A:A,customers!F:F) -> Los Angeles | L11: =_xlfn.XLOOKUP(F11,customers!A:A,customers!G:G) -> United States | M11: =_xlfn.XLOOKUP(G11,products!A:A,products!B:B) -> Rob | N11: =_xlfn.XLOOKUP(G11,products!A:A,products!C:C) -> M | O11: =_xlfn.XLOOKUP(G11,products!A:A,products!D:D) -> 0.5 | P11: =_xlfn.XLOOKUP(G11,products!A:A,products!E:E) -> 5.97 | Q11: =P11*H11 -> 5.97 | R11: {=_xlfn.IFS(Q11<=50,"low sales",Q11<=100,"medium sales",Q11>100,"High sales")} -> low sales
A12: BKK-47233-845 | B12: 44263 | C12: =TEXT(B12,"DDDD") -> Monday | D12: =TEXT(B12,"MMMM") -> March | E12: =TEXT(B12,"YYYY") -> 2021 | F12: 76239-90137-UQ | G12: A-D-1 | H12: 4 | I12: =_xlfn.XLOOKUP(F12,customers!A:A,customers!B:B) -> Ferrell Ferber | J12: =_xlfn.XLOOKUP(F12,customers!A:A,customers!C:C) -> fferbera@businesswire.com | K12: =_xlfn.XLOOKUP(F12,customers!A:A,customers!F:F) -> San Jose | L12: =_xlfn.XLOOKUP(F12,customers!A:A,customers!G:G) -> United States | M12: =_xlfn.XLOOKUP(G12,products!A:A,products!B:B) -> Ara | N12: =_xlfn.XLOOKUP(G12,products!A:A,products!C:C) -> D | O12: =_xlfn.XLOOKUP(G12,products!A:A,products!D:D) -> 1 | P12: =_xlfn.XLOOKUP(G12,products!A:A,products!E:E) -> 9.95 | Q12: =P12*H12 -> 39.8 | R12: {=_xlfn.IFS(Q12<=50,"low sales",Q12<=100,"medium sales",Q12>100,"High sales")} -> low sales
A13: VQR-01002-970 | B13: 44132 | C13: =TEXT(B13,"DDDD") -> Wednesday | D13: =TEXT(B13,"MMMM") -> October | E13: =TEXT(B13,"YYYY") -> 2020 | F13: 49315-21985-BB | G13: E-L-2.5 | H13: 5 | I13: =_xlfn.XLOOKUP(F13,customers!A:A,customers!B:B) -> Duky Phizackerly | J13: =_xlfn.XLOOKUP(F13,customers!A:A,customers!C:C) -> dphizackerlyb@utexas.edu | K13: =_xlfn.XLOOKUP(F13,customers!A:A,customers!F:F) -> San Jose | L13: =_xlfn.XLOOKUP(F13,customers!A:A,customers!G:G) -> United States | M13: =_xlfn.XLOOKUP(G13,products!A:A,products!B:B) -> Exc | N13: =_xlfn.XLOOKUP(G13,products!A:A,products!C:C) -> L | O13: =_xlfn.XLOOKUP(G13,products!A:A,products!D:D) -> 2.5 | P13: =_xlfn.XLOOKUP(G13,products!A:A,products!E:E) -> 34.155 | Q13: =P13*H13 -> 170.775 | R13: {=_xlfn.IFS(Q13<=50,"low sales",Q13<=100,"medium sales",Q13>100,"High sales")} -> High sales
... A1001: IRV-20769-219 | B1001: 44119 | C1001: =TEXT(B1001,"DDDD") -> Thursday | D1001: =TEXT(B1001,"MMMM") -> October | E1001: =TEXT(B1001,"YYYY") -> 2020 | F1001: 77131-58092-GE | G1001: E-M-0.2 | H1001: 3 | I1001: =_xlfn.XLOOKUP(F1001,customers!A:A,customers!B:B) -> Vidovic Antonelli | J1001: =_xlfn.XLOOKUP(F1001,customers!A:A,customers!C:C) -> 0 | K1001: =_xlfn.XLOOKUP(F1001,customers!A:A,customers!F:F) -> London | L1001: =_xlfn.XLOOKUP(F1001,customers!A:A,customers!G:G) -> United Kingdom | M1001: =_xlfn.XLOOKUP(G1001,products!A:A,products!B:B) -> Exc | N1001: =_xlfn.XLOOKUP(G1001,products!A:A,products!C:C) -> M | O1001: =_xlfn.XLOOKUP(G1001,products!A:A,products!D:D) -> 0.2 | P1001: =_xlfn.XLOOKUP(G1001,products!A:A,products!E:E) -> 4.125 | Q1001: =P1001*H1001 -> 12.375 | R1001: {=_xlfn.IFS(Q1001<=50,"low sales",Q1001<=100,"medium sales",Q1001>100,"High sales")} -> low sales

Sheet customers
A1: Customer ID | B1: Customer Name | C1: Email | D1: Phone Number | E1: Address Line 1 | F1: City | G1: Country | H1: Postcode | I1: Loyalty Card
A2: 17670-51384-MA | B2: Aloisia Allner | C2: aallner0@lulu.com | D2: +1 (862) 817-0124 | E2: 57999 Pepper Wood Alley | F2: Paterson | G2: United States | H2: 7505 | I2: Yes
A3: 73342-18763-UW | B3: Piotr Bote | C3: pbote1@yelp.com | D3: +353 (913) 396-4653 | E3: 2112 Ridgeway Hill | F3: Crumlin | G3: Ireland | H3: D6W | I3: No
A4: 21125-22134-PX | B4: Jami Redholes | C4: jredholes2@tmall.com | D4: +1 (210) 986-6806 | E4: 5214 Bartillon Park | F4: San Antonio | G4: United States | H4: 78205 | I4: Yes
A5: 71253-00052-RN | B5: Dene Azema | C5: dazema3@facebook.com | D5: +1 (217) 418-0714 | E5: 27 Maywood Place | F5: Springfield | G5: United States | H5: 62711 | I5: Yes
A6: 23806-46781-OU | B6: Christoffer O' Shea | D6: +353 (698) 362-9201 | E6: 38980 Manitowish Junction | F6: Cill Airne | G6: Ireland | H6: N41 | I6: No
A7: 86561-91660-RB | B7: Beryle Cottier | D7: +1 (570) 289-7473 | E7: 2651 Stoughton Place | F7: Scranton | G7: United States | H7: 18505 | I7: No
A8: 65223-29612-CB | B8: Shaylynn Lobe | C8: slobe6@nifty.com | D8: +1 (937) 954-4541 | E8: 7005 Mariners Cove Place | F8: Dayton | G8: United States | H8: 45440 | I8: Yes
A9: 21134-81676-FR | B9: Melvin Wharfe | D9: +353 (507) 574-3034 | E9: 7 Straubel Road | F9: Kill | G9: Ireland | H9: P24 | I9: Yes
A10: 03396-68805-ZC | B10: Guthrey Petracci | C10: gpetracci8@livejournal.com | D10: +1 (310) 868-1842 | E10: 949 Paget Parkway | F10: Los Angeles | G10: United States | H10: 90045 | I10: No
A11: 61021-27840-ZN | B11: Rodger Raven | C11: rraven9@ed.gov | D11: +1 (213) 263-0288 | E11: 1 Reinke Avenue | F11: Los Angeles | G11: United States | H11: 90065 | I11: No
A12: 76239-90137-UQ | B12: Ferrell Ferber | C12: fferbera@businesswire.com | D12: +1 (408) 383-5302 | E12: 68 High Crossing Court | F12: San Jose | G12: United States | H12: 95160 | I12: No
A13: 49315-21985-BB | B13: Duky Phizackerly | C13: dphizackerlyb@utexas.edu | D13: +1 (408) 533-6012 | E13: 28643 Bluejay Crossing | F13: San Jose | G13: United States | H13: 95194 | I13: Yes
A14: 34136-36674-OM | B14: Rosaleen Scholar | C14: rscholarc@nyu.edu | D14: +1 (804) 420-0420 | E14: 80915 Montana Park | F14: Richmond | G14: United States | H14: 23285 | I14: No
A15: 39396-12890-PE | B15: Terence Vanyutin | C15: tvanyutind@wix.com | E15: 331 Bunting Hill | F15: Migrate | G15: United States | H15: 41905 | I15: No
A16: 95875-73336-RG | B16: Patrice Trobe | C16: ptrobee@wunderground.com | D16: +1 (314) 240-7896 | E16: 827 Declaration Plaza | F16: Saint Louis | G16: United States | H16: 63131 | I16: Yes
A17: 25473-43727-BY | B17: Llywellyn Oscroft | C17: loscroftf@ebay.co.uk | E17: 022 Roth Place | F17: Philadelphia | G17: United States | H17: 19172 | I17: No
A18: 99643-51048-IQ | B18: Minni Alabaster | C18: malabasterg@hexun.com | D18: +1 (971) 483-6255 | E18: 3 Charing Cross Trail | F18: Portland | G18: United States | H18: 97271 | I18: No
A19: 62173-15287-CU | B19: Rhianon Broxup | C19: rbroxuph@jimdo.com | D19: +1 (713) 663-1338 | E19: 83517 Thierer Court | F19: Houston | G19: United States | H19: 77240 | I19: No
A20: 57611-05522-ST | B20: Pall Redford | C20: predfordi@ow.ly | E20: 7337 Hayes Junction | F20: Caherconlish | G20: Ireland | H20: F45 | I20: Yes
A21: 76664-37050-DT | B21: Aurea Corradino | C21: acorradinoj@harvard.edu | D21: +1 (646) 202-5965 | E21: 698 Canary Terrace | F21: New York City | G21: United States | H21: 10060 | I21: Yes
A22: 84565-53984-SX | B22: Kendal Scardefield | D22: +353 (733) 405-3302 | E22: 3 Northridge Crossing | F22: Clondalkin | G22: Ireland | H22: D24 | I22: Yes
A23: 03090-88267-BQ | B23: Avrit Davidowsky | C23: adavidowskyl@netvibes.com | D23: +1 (616) 481-9962 | E23: 9 Warrior Junction | F23: Grand Rapids | G23: United States | H23: 49560 | I23: No
A24: 37651-47492-NC | B24: Annabel Antuk | C24: aantukm@kickstarter.com | D24: +1 (941) 740-6268 | E24: 77965 Lawn Park | F24: Punta Gorda | G24: United States | H24: 33982 | I24: Yes
A25: 95399-57205-HI | B25: Iorgo Kleinert | C25: ikleinertn@timesonline.co.uk | D25: +1 (360) 352-6598 | E25: 1 Morningstar Lane | F25: Vancouver | G25: United States | H25: 98682 | I25: Yes
A26: 24010-66714-HW | B26: Chrisy Blofeld | C26: cblofeldo@amazon.co.uk | D26: +1 (303) 936-3357 | E26: 013 Talisman Terrace | F26: Englewood | G26: United States | H26: 80150 | I26: No
A27: 07591-92789-UA | B27: Culley Farris | D27: +1 (941) 267-4822 | E27: 4 Mitchell Drive | F27: Punta Gorda | G27: United States | H27: 33982 | I27: Yes
A28: 49231-44455-IC | B28: Selene Shales | C28: sshalesq@umich.edu | D28: +1 (707) 881-5004 | E28: 74 Bultman Plaza | F28: Petaluma | G28: United States | H28: 94975 | I28: Yes
A29: 50124-88608-EO | B29: Vivie Danneil | C29: vdanneilr@mtv.com | D29: +353 (751) 346-0399 | E29: 5626 Darwin Avenue | F29: Tralee | G29: Ireland | H29: V92 | I29: No
A30: 00888-74814-UZ | B30: Theresita Newbury | C30: tnewburys@usda.gov | D30: +353 (803) 587-0026 | E30: 79526 Bultman Lane | F30: Clonskeagh | G30: Ireland | H30: D04 | I30: No
A31: 14158-30713-OB | B31: Mozelle Calcutt | C31: mcalcuttt@baidu.com | D31: +353 (928) 869-1762 | E31: 4389 Russell Way | F31: Rathwire | G31: Ireland | H31: Y25 | I31: Yes
A32: 51427-89175-QJ | B32: Adrian Swaine | D32: +1 (303) 486-9517 | E32: 95 Straubel Hill | F32: Aurora | G32: United States | H32: 80044 | I32: No
A33: 52082-49024-ON | B33: Ray Leivesley | C33: rleivesleyv@canalblog.com | D33: +1 (212) 535-7791 | E33: 91 Stephen Drive | F33: Jamaica | G33: United States | H33: 11407 | I33: No
A34: 04540-43685-DV | B34: Nelly Basezzi | C34: nbasezziw@webeden.co.uk | D34: +353 (125) 815-7345 | E34: 923 Mallard Junction | F34: Bailieborough | G34: Ireland | H34: C15 | I34: Yes
A35: 39123-12846-YJ | B35: Gallard Gatheral | C35: ggatheralx@123-reg.co.uk | E35: 40 Clemons Place | F35: Grand Forks | G35: United States | H35: 58207 | I35: No
A36: 44981-99666-XB | B36: Una Welberry | C36: uwelberryy@ebay.co.uk | D36: +44 (392) 503-8132 | E36: 40915 Schlimgen Park | F36: Upton | G36: United Kingdom | H36: DN21 | I36: Yes
A37: 24825-51803-CQ | B37: Faber Eilhart | C37: feilhartz@who.int | D37: +1 (304) 510-6095 | E37: 6966 Victoria Street | F37: Charleston | G37: United States | H37: 25362 | I37: No
A38: 77634-13918-GJ | B38: Zorina Ponting | C38: zponting10@altervista.org | D38: +1 (501) 172-1476 | E38: 7118 Holmberg Court | F38: Little Rock | G38: United States | H38: 72204 | I38: No
A39: 13694-25001-LX | B39: Silvio Strase | C39: sstrase11@booking.com | D39: +1 (303) 579-8015 | E39: 5 Forest Lane | F39: Denver | G39: United States | H39: 80291 | I39: No
A40: 08523-01791-TI | B40: Dorie de la Tremoille | C40: dde12@unesco.org | D40: +1 (612) 492-5160 | E40: 0817 Dennis Street | F40: Minneapolis | G40: United States | H40: 55458 | I40: No
A41: 49860-68865-AB | B41: Hy Zanetto | E41: 469 Paget Place | F41: Tucson | G41: United States | H41: 85715 | I41: Yes
A42: 21240-83132-SP | B42: Jessica McNess | D42: +1 (504) 545-1478 | E42: 664 Erie Place | F42: New Orleans | G42: United States | H42: 70116 | I42: No
A43: 08350-81623-TF | B43: Lorenzo Yeoland | C43: lyeoland15@pbs.org | D43: +1 (860) 576-2887 | E43: 8510 Merrick Road | F43: Hartford | G43: United States | H43: 6183 | I43: Yes
A44: 73284-01385-SJ | B44: Abigail Tolworthy | C44: atolworthy16@toplist.cz | D44: +1 (801) 722-4425 | E44: 74 Shopko Way | F44: Ogden | G44: United States | H44: 84409 | I44: Yes
A45: 04152-34436-IE | B45: Maurie Bartol | D45: +1 (617) 493-7594 | E45: 7625 Starling Court | F45: Boston | G45: United States | H45: 2216 | I45: No
A46: 06631-86965-XP | B46: Olag Baudassi | C46: obaudassi18@seesaa.net | D46: +1 (585) 356-6251 | E46: 55 Dottie Court | F46: Rochester | G46: United States | H46: 14604 | I46: Yes
A47: 54619-08558-ZU | B47: Petey Kingsbury | C47: pkingsbury19@comcast.net | D47: +1 (917) 705-8224 | E47: 28 Loftsgordon Place | F47: Bronx | G47: United States | H47: 10469 | I47: No
A48: 85589-17020-CX | B48: Donna Baskeyfied | D48: +1 (205) 923-1460 | E48: 7586 Logan Avenue | F48: Birmingham | G48: United States | H48: 35205 | I48: Yes
A49: 36078-91009-WU | B49: Arda Curley | C49: acurley1b@hao123.com | D49: +1 (760) 840-3808 | E49: 45098 Scott Drive | F49: San Bernardino | G49: United States | H49: 92415 | I49: Yes
A50: 15770-27099-GX | B50: Raynor McGilvary | C50: rmcgilvary1c@tamu.edu | E50: 496 Rockefeller Court | F50: Norfolk | G50: United States | H50: 23514 | I50: No
A51: 91460-04823-BX | B51: Isis Pikett | C51: ipikett1d@xinhuanet.com | D51: +1 (202) 871-9039 | E51: 5892 Hauk Drive | F51: Washington | G51: United States | H51: 20409 | I51: No
A52: 45089-52817-WN | B52: Inger Bouldon | C52: ibouldon1e@gizmodo.com | D52: +1 (754) 391-4736 | E52: 925 Barby Circle | F52: Fort Lauderdale | G52: United States | H52: 33355 | I52: No
A53: 76447-50326-IC | B53: Karry Flanders | C53: kflanders1f@over-blog.com | D53: +353 (467) 720-7274 | E53: 88 Blue Bill Park Avenue | F53: Crumlin | G53: Ireland | H53: D6W | I53: Yes
A54: 26333-67911-OL | B54: Hartley Mattioli | C54: hmattioli1g@webmd.com | E54: 126 Valley Edge Street | F54: Kinloch | G54: United Kingdom | H54: PH43 | I54: No
A55: 40768-49176-BL | B55: Horatio Rubberts | C55: hrubberts1h@google.com.hk | D55: +1 (801) 635-8791 | E55: 459 Russell Center | F55: Provo | G55: United States | H55: 84605 | I55: No
A56: 22107-86640-SB | B56: Archambault Gillard | C56: agillard1i@issuu.com | D56: +1 (419) 663-2236 | E56: 97490 Susan Avenue | F56: Toledo | G56: United States | H56: 43666 | I56: No
A57: 09960-34242-LZ | B57: Salomo Cushworth | D57: +1 (609) 409-7044 | E57: 44 Oneill Parkway | F57: Trenton | G57: United States | H57: 8650 | I57: No
A58: 04671-85591-RT | B58: Theda Grizard | C58: tgrizard1k@odnoklassniki.ru | D58: +1 (813) 243-2150 | E58: 6 Knutson Pass | F58: Tampa | G58: United States | H58: 33686 | I58: Yes
A59: 25729-68859-UA | B59: Rozele Relton | C59: rrelton1l@stanford.edu | D59: +1 (850) 626-1181 | E59: 2484 Reindahl Court | F59: Pensacola | G59: United States | H59: 32590 | I59: No
A60: 05501-86351-NX | B60: Willa Rolling | D60: +1 (813) 759-3534 | E60: 3 Mockingbird Plaza | F60: Zephyrhills | G60: United States | H60: 33543 | I60: Yes
A61: 04521-04300-OK | B61: Stanislaus Gilroy | C61: sgilroy1n@eepurl.com | E61: 9120 Harbort Terrace | F61: Saint Paul | G61: United States | H61: 55123 | I61: Yes
A62: 58689-55264-VK | B62: Correy Cottingham | C62: ccottingham1o@wikipedia.org | D62: +1 (260) 764-1820 | E62: 394 Logan Road | F62: Fort Wayne | G62: United States | H62: 46862 | I62: No
A63: 79436-73011-MM | B63: Pammi Endacott | D63: +44 (177) 260-5076 | E63: 5841 Atwood Lane | F63: Wootton | G63: United Kingdom | H63: NN4 | I63: Yes
A64: 65552-60476-KY | B64: Nona Linklater | D64: +1 (239) 347-9766 | E64: 856 Bonner Parkway | F64: Naples | G64: United States | H64: 34114 | I64: Yes
A65: 69904-02729-YS | B65: Annadiane Dykes | C65: adykes1r@eventbrite.com | D65: +1 (312) 111-6203 | E65: 31 Northport Terrace | F65: Chicago | G65: United States | H65: 60681 | I65: No
A66: 01433-04270-AX | B66: Felecia Dodgson | D66: +1 (973) 434-8662 | E66: 48053 8th Crossing | F66: Newark | G66: United States | H66: 7104 | I66: Yes
A67: 14204-14186-LA | B67: Angelia Cockrem | C67: acockrem1t@engadget.com | D67: +1 (571) 316-8217 | E67: 1 Sherman Alley | F67: Vienna | G67: United States | H67: 22184 | I67: Yes
A68: 32948-34398-HC | B68: Belvia Umpleby | C68: bumpleby1u@soundcloud.com | D68: +1 (682) 627-0888 | E68: 710 Prairie Rose Terrace | F68: Fort Worth | G68: United States | H68: 76178 | I68: Yes
A69: 77343-52608-FF | B69: Nat Saleway | C69: nsaleway1v@dedecms.com | D69: +1 (323) 473-0294 | E69: 0780 Anthes Plaza | F69: Burbank | G69: United States | H69: 91505 | I69: No
A70: 42770-36274-QA | B70: Hayward Goulter | C70: hgoulter1w@abc.net.au | D70: +1 (423) 764-7751 | E70: 2081 Mariners Cove Drive | F70: Kingsport | G70: United States | H70: 37665 | I70: No
A71: 14103-58987-ZU | B71: Gay Rizzello | C71: grizzello1x@symantec.com | D71: +44 (247) 225-8003 | E71: 21 Schmedeman Crossing | F71: Liverpool | G71: United Kingdom | H71: L33 | I71: Yes
A72: 69958-32065-SW | B72: Shannon List | C72: slist1y@mapquest.com | D72: +1 (614) 279-9816 | E72: 7123 Algoma Center | F72: Columbus | G72: United States | H72: 43231 | I72: No
A73: 69533-84907-FA | B73: Shirlene Edmondson | C73: sedmondson1z@theguardian.com | D73: +353 (248) 428-7978 | E73: 4752 International Point | F73: Newmarket on Fergus | G73: Ireland | H73: P17 | I73: No
A74: 76005-95461-CI | B74: Aurlie McCarl | D74: +1 (504) 209-2724 | E74: 731 David Park | F74: New Orleans | G74: United States | H74: 70183 | I74: No
A75: 15395-90855-VB | B75: Alikee Carryer | D75: +1 (704) 799-5219 | E75: 247 Helena Drive | F75: Charlotte | G75: United States | H75: 28230 | I75: Yes
A76: 80640-45811-LB | B76: Jennifer Rangall | C76: jrangall22@newsvine.com | D76: +1 (781) 512-6637 | E76: 0 Grasskamp Lane | F76: Springfield | G76: United States | H76: 1114 | I76: Yes
A77: 28476-04082-GR | B77: Kipper Boorn | C77: kboorn23@ezinearticles.com | D77: +353 (359) 134-1550 | E77: 9513 Meadow Ridge Parkway | F77: Listowel | G77: Ireland | H77: V31 | I77: Yes
A78: 12018-75670-EU | B78: Melania Beadle | D78: +353 (569) 458-9673 | E78: 4418 Quincy Terrace | F78: Moycullen | G78: Ireland | H78: A41 | I78: Yes
A79: 86437-17399-FK | B79: Colene Elgey | C79: celgey25@webs.com | D79: +1 (432) 261-0702 | E79: 45 Marcy Crossing | F79: Midland | G79: United States | H79: 79705 | I79: No
A80: 62979-53167-ML | B80: Lothaire Mizzi | C80: lmizzi26@rakuten.co.jp | D80: +1 (214) 719-8530 | E80: 74 Atwood Lane | F80: Dallas | G80: United States | H80: 75323 | I80: Yes
A81: 54810-81899-HL | B81: Cletis Giacomazzo | C81: cgiacomazzo27@jigsy.com | D81: +1 (571) 703-2064 | E81: 817 Ridgeway Hill | F81: Dulles | G81: United States | H81: 20189 | I81: No
A82: 26103-41504-IB | B82: Ami Arnow | C82: aarnow28@arizona.edu | D82: +1 (650) 238-1964 | E82: 12 Oakridge Court | F82: Oakland | G82: United States | H82: 94627 | I82: Yes
A83: 76534-45229-SG | B83: Sheppard Yann | C83: syann29@senate.gov | D83: +1 (719) 803-5276 | E83: 4 Farmco Place | F83: Colorado Springs | G83: United States | H83: 80930 | I83: Yes
A84: 81744-27332-RR | B84: Bunny Naulls | C84: bnaulls2a@tiny.cc | D84: +353 (809) 128-0755 | E84: 595 Melby Avenue | F84: Adare | G84: Ireland | H84: H54 | I84: Yes
A85: 91513-75657-PH | B85: Hally Lorait | D85: +1 (716) 869-3749 | E85: 80 Jana Avenue | F85: Buffalo | G85: United States | H85: 14205 | I85: Yes
A86: 30373-66619-CB | B86: Zaccaria Sherewood | C86: zsherewood2c@apache.org | D86: +1 (209) 433-7924 | E86: 1325 Jay Terrace | F86: Fresno | G86: United States | H86: 93715 | I86: No
A87: 31582-23562-FM | B87: Jeffrey Dufaire | C87: jdufaire2d@fc2.com | E87: 8 Buell Junction | F87: Fort Worth | G87: United States | H87: 76121 | I87: No
A88: 58638-01029-CB | B88: Blancha McAmish | C88: bmcamish2e@tripadvisor.com | E88: 5484 Stephen Court | F88: Oklahoma City | G88: United States | H88: 73179 | I88: Yes
A89: 81431-12577-VD | B89: Beitris Keaveney | C89: bkeaveney2f@netlog.com | E89: 67319 Redwing Parkway | F89: Beaumont | G89: United States | H89: 77705 | I89: No
A90: 68894-91205-MP | B90: Elna Grise | C90: egrise2g@cargocollective.com | E90: 92 Becker Circle | F90: Reno | G90: United States | H90: 89519 | I90: No
A91: 87602-55754-VN | B91: Torie Gottelier | C91: tgottelier2h@vistaprint.com | D91: +1 (816) 743-8492 | E91: 426 Division Avenue | F91: Kansas City | G91: United States | H91: 64136 | I91: No
A92: 39181-35745-WH | B92: Loydie Langlais | D92: +353 (576) 222-5069 | E92: 290 Ilene Street | F92: Crumlin | G92: Ireland | H92: D6W | I92: Yes
A93: 30381-64762-NG | B93: Adham Greenhead | C93: agreenhead2j@dailymail.co.uk | D93: +1 (951) 797-0738 | E93: 0062 Spenser Place | F93: Corona | G93: United States | H93: 92878 | I93: No
A94: 17503-27693-ZH | B94: Hamish MacSherry | D94: +1 (512) 430-4374 | E94: 7 Brentwood Plaza | F94: Austin | G94: United States | H94: 78759 | I94: Yes
A95: 89442-35633-HJ | B95: Else Langcaster | C95: elangcaster2l@spotify.com | D95: +44 (547) 590-3103 | E95: 3658 Jenna Street | F95: Normanton | G95: United Kingdom | H95: LE15 | I95: Yes
A96: 13654-85265-IL | B96: Rudy Farquharson | E96: 30178 Claremont Road | F96: Charlesland | G96: Ireland | H96: A63 | I96: Yes
A97: 40946-22090-FP | B97: Norene Magauran | C97: nmagauran2n@51.la | E97: 567 Artisan Place | F97: Fresno | G97: United States | H97: 93762 | I97: No
A98: 29050-93691-TS | B98: Vicki Kirdsch | C98: vkirdsch2o@google.fr | E98: 0263 Golf Street | F98: Saint Louis | G98: United States | H98: 63150 | I98: No
A99: 64395-74865-WF | B99: Ilysa Whapple | C99: iwhapple2p@com.com | D99: +1 (559) 522-1152 | E99: 41598 Everett Drive | F99: Fresno | G99: United States | H99: 93726 | I99: No
A100: 81861-66046-SU | B100: Ruy Cancellieri | D100: +353 (338) 743-8327 | E100: 251 Welch Parkway | F100: Confey | G100: Ireland | H100: A86 | I100: No
...

Sheet products
A1: Product ID | B1: Coffee Type | C1: Roast Type | D1: Size | E1: Unit Price | F1: Price per 100g | G1: Profit
A2: A-L-0.2 | B2: Ara | C2: L | D2: 0.2 | E2: 3.885 | F2: 1.9425 | G2: 0.34965
A3: A-L-0.5 | B3: Ara | C3: L | D3: 0.5 | E3: 7.77 | F3: 1.554 | G3: 0.6993
A4: A-L-1 | B4: Ara | C4: L | D4: 1 | E4: 12.95 | F4: 1.295 | G4: 1.1655
A5: A-L-2.5 | B5: Ara | C5: L | D5: 2.5 | E5: 29.785 | F5: 1.1914 | G5: 2.68065
A6: A-M-0.2 | B6: Ara | C6: M | D6: 0.2 | E6: 3.375 | F6: 1.6875 | G6: 0.30375
A7: A-M-0.5 | B7: Ara | C7: M | D7: 0.5 | E7: 6.75 | F7: 1.35 | G7: 0.6075
A8: A-M-1 | B8: Ara | C8: M | D8: 1 | E8: 11.25 | F8: 1.125 | G8: 1.0125
A9: A-M-2.5 | B9: Ara | C9: M | D9: 2.5 | E9: 25.875 | F9: 1.035 | G9: 2.32875
A10: A-D-0.2 | B10: Ara | C10: D | D10: 0.2 | E10: 2.985 | F10: 1.4925 | G10: 0.26865
A11: A-D-0.5 | B11: Ara | C11: D | D11: 0.5 | E11: 5.97 | F11: 1.194 | G11: 0.5373
A12: A-D-1 | B12: Ara | C12: D | D12: 1 | E12: 9.95 | F12: 0.995 | G12: 0.8955
A13: A-D-2.5 | B13: Ara | C13: D | D13: 2.5 | E13: 22.885 | F13: 0.9154 | G13: 2.05965
... A49: E-D-2.5 | B49: Exc | C49: D | D49: 2.5 | E49: 27.945 | F49: 1.1178 | G49: 3.07395

Sheet Sheet9
